{
    "configurations": [
        {
            "name": "Win32",
            "includePath": [
                "${workspaceFolder}/**",
                "${workspaceFolder}/include/**"
            ],
            "defines": [
                "DEBUG_TIME",
                "ENET_IMPLEMENTATION"
            ],
            "compilerPath": "c:/msys64/ucrt64/bin/g++.exe",
            "compilerArgs": [
                "-std=c++26",
                "-g",
                "-Iinclude",
                "-MMD",
                "-MP",
                "-DDEBUG_TIME"
            ],
            "cStandard": "c23",
            "cppStandard": "c++26",
            "intelliSenseMode": "windows-gcc-x64"
        }
    ],
    "version": 4
}